SkateTracker/__init__.py
SkateTracker/art.py
SkateTracker/layout.py
SkateTracker/main.py
SkateTracker/plot.py
SkateTracker/utils.py
SkateTracker-0.1.3.dist-info/LICENSE
SkateTracker-0.1.3.dist-info/METADATA
SkateTracker-0.1.3.dist-info/WHEEL
SkateTracker-0.1.3.dist-info/entry_points.txt
SkateTracker-0.1.3.dist-info/top_level.txt
SkateTracker-0.1.3.dist-info/RECORD
