Metadata-Version: 2.1
Name: SkateTracker
Version: 0.1.3
Summary: CLI tool to track speed skating races
Home-page: https://github.com/HiddeFok/CLI_speed_skating_tracker
Author: Hidde Fokkema
License: MIT
Keywords: CLI sports visualization
Platform: UNKNOWN
Requires-Python: >=3.5
License-File: LICENSE
Requires-Dist: numpy (>=1.18.4)
Requires-Dist: plotext (>=4.0.0)
Requires-Dist: rich (>=11.0.0)
